pdp11games/__init__.py
pdp11games/marswar.py
pdp11games/sp21.py
pdp11games/xonix.py
pdp11games-1.0.dist-info/DESCRIPTION.rst
pdp11games-1.0.dist-info/METADATA
pdp11games-1.0.dist-info/RECORD
pdp11games-1.0.dist-info/WHEEL
pdp11games-1.0.dist-info/entry_points.txt
pdp11games-1.0.dist-info/metadata.json
pdp11games-1.0.dist-info/top_level.txt
