Metadata-Version: 2.0
Name: pdp11games
Version: 1.0
Summary: Reimplementations of old PDP-11 console games
Home-page: https://savannah.nongnu.org/projects/pdp11games
Author: Peter Cherepanov
Author-email: mathmoth@mathmoth.org
License: UNKNOWN
Keywords: retro retrocomputing pacman pdp11 game console CLI curses ncurses
Platform: UNKNOWN
Classifier: Programming Language :: Python :: 3
Classifier: Development Status :: 4 - Beta
Classifier: License :: OSI Approved :: GNU General Public License v3 (GPLv3)
Classifier: Environment :: Console :: Curses
Classifier: Operating System :: OS Independent
Classifier: Intended Audience :: End Users/Desktop
Classifier: Natural Language :: English
Classifier: Operating System :: POSIX :: Linux
Classifier: Operating System :: MacOS :: MacOS X
Classifier: Topic :: Games/Entertainment
Requires-Python: >=3
